[
  {
    "title": "mynameisntjmack & Tommy Richman - numbersnshit [Official Visualizer]",
    "id": "QxCB3P35EuQ",
    "duration": "2:15",
    "author": "mynameisntjmack",
    "views": "55,614 views",
    "published": "3 years ago",
    "thumbnail": "https://i.ytimg.com/vi/QxCB3P35EuQ/hq720.jpg?sqp=-oaymwExCNAFEJQDSFryq4qpAyMIARUAAIhCGAHwAQH4Af4JgALQBYoCDAgAEAEYWCBbKGUwDw==&rs=AOn4CLC3SMEZNs7xlGYZ3l8YylCkawYR6g",
    "timestamp": 1777298430.117157
  },
  {
    "title": "Tommy Richman - BOTHER ME (feat. Brent Faiyaz)",
    "id": "ARIZb6rGK0M",
    "duration": "2:36",
    "author": "Tommy Richman",
    "views": "1,376,692 views",
    "published": "5mo ago",
    "thumbnail": "https://i.ytimg.com/vi/ARIZb6rGK0M/hq720.jpg?sqp=-oaymwEXCNAFEJQDSFryq4qpAwkIARUAAIhCGAE=&rs=AOn4CLCPq4ubAOiXO0UycUpcKqlRYC7bEw",
    "timestamp": 1777298416.153687
  }
]
